cleanshot/constants.py
cleanshot/main.py
cleanshot/config/__init__.py
cleanshot/config/setup.py
cleanshot/config/types.py
cleanshot/core/__init__.py
cleanshot/core/cleanshot.py
cleanshot/core/monitor.py
cleanshot/core/rename.py
cleanshot/llms/__init__.py
cleanshot/llms/inference_provider_base.py
cleanshot/llms/llm.py
cleanshot/llms/types.py
cleanshot/llms/openai/__init__.py
cleanshot/llms/openai/provider.py
cleanshot/llms/openai/setup.py
cleanshot/utils/logging.py
cleanshot/utils/utils.py
cleanshot-1.2.0.dist-info/licenses/LICENSE
cleanshot-1.2.0.dist-info/METADATA
cleanshot-1.2.0.dist-info/WHEEL
cleanshot-1.2.0.dist-info/entry_points.txt
cleanshot-1.2.0.dist-info/top_level.txt
cleanshot-1.2.0.dist-info/RECORD
