Metadata-Version: 2.4
Name: cleanshot
Version: 1.2.0
Summary: A tool to automatically rename screenshots using OpenAI's OCR
Author: Shlomo Dahan
License-Expression: MIT
Project-URL: Repository, https://github.com/shlomomdahan/cleanshot
Requires-Python: >=3.8
License-File: LICENSE
Requires-Dist: watchdog>=6.0.0
Requires-Dist: openai>=1.76.0
Requires-Dist: python-dotenv>=1.1.0
Requires-Dist: Pillow>=11.2.1
Requires-Dist: questionary>=1.10.0
Requires-Dist: rich>=13.9.4
Provides-Extra: dev
Requires-Dist: ruff>=0.11.7; extra == "dev"
Dynamic: license-file
